reconlib/__init__.py
reconlib/core/base.py
reconlib/core/exceptions.py
reconlib/core/utils/user_agents.py
reconlib/core/utils/user_agents_list.txt
reconlib/core/utils/validation.py
reconlib/crtsh/api.py
reconlib/hackertarget/api.py
reconlib/virustotal/api.py
reconlib-0.5.0.dist-info/METADATA
reconlib-0.5.0.dist-info/LICENSE
reconlib-0.5.0.dist-info/WHEEL
reconlib-0.5.0.dist-info/RECORD
